bayes_lol_client/__init__.py
bayes_lol_client/api.py
bayes_lol_client/emh.py
bayes_lol_client/errors.py
bayes_lol_client/historic.py
bayes_lol_client/sleep.py
bayes_lol_client/utils.py
bayes_lol_client-1.0.3.dist-info/LICENSE
bayes_lol_client-1.0.3.dist-info/WHEEL
bayes_lol_client-1.0.3.dist-info/METADATA
bayes_lol_client-1.0.3.dist-info/RECORD
