Metadata-Version: 2.1
Name: bayes-lol-client
Version: 1.0.3
Summary: Wrapper for Bayes League of Legends API
Home-page: https://github.com/arbolitoloco1/bayes_lol_client
License: GPL-3.0-or-later
Author: Santiago Kozak
Author-email: kozaksantiago@gmail.com
Requires-Python: >=3.9,<4.0
Classifier: License :: OSI Approved :: GNU General Public License v3 or later (GPLv3+)
Classifier: Programming Language :: Python :: 3
Classifier: Programming Language :: Python :: 3.9
Classifier: Programming Language :: Python :: 3.10
Classifier: Programming Language :: Python :: 3.11
Requires-Dist: pytz (>=2022.7,<2023.0)
Requires-Dist: requests (>=2.28.1,<3.0.0)
